MANIFEST.in
README.txt
setup.cfg
setup.py
docs/HISTORY.txt
pcommerce/__init__.py
pcommerce.shipment.pickup.egg-info/PKG-INFO
pcommerce.shipment.pickup.egg-info/SOURCES.txt
pcommerce.shipment.pickup.egg-info/dependency_links.txt
pcommerce.shipment.pickup.egg-info/entry_points.txt
pcommerce.shipment.pickup.egg-info/namespace_packages.txt
pcommerce.shipment.pickup.egg-info/not-zip-safe
pcommerce.shipment.pickup.egg-info/requires.txt
pcommerce.shipment.pickup.egg-info/top_level.txt
pcommerce/shipment/__init__.py
pcommerce/shipment/pickup/__init__.py
pcommerce/shipment/pickup/configure.zcml
pcommerce/shipment/pickup/data.py
pcommerce/shipment/pickup/interfaces.py
pcommerce/shipment/pickup/plugin.py
pcommerce/shipment/pickup/browser/__init__.py
pcommerce/shipment/pickup/browser/base.py
pcommerce/shipment/pickup/browser/configure.zcml
pcommerce/shipment/pickup/browser/confirmation.pt
pcommerce/shipment/pickup/browser/confirmation.py
pcommerce/shipment/pickup/browser/icon.gif
pcommerce/shipment/pickup/browser/logo.gif
pcommerce/shipment/pickup/browser/overview.pt
pcommerce/shipment/pickup/browser/overview.py
pcommerce/shipment/pickup/browser/shipment.py
pcommerce/shipment/pickup/i18n/pcommerce-de.mo
pcommerce/shipment/pickup/i18n/pcommerce-de.po
pcommerce/shipment/pickup/i18n/pcommerce-fr.mo
pcommerce/shipment/pickup/i18n/pcommerce-fr.po
pcommerce/shipment/pickup/i18n/pcommerce-nl.mo
pcommerce/shipment/pickup/i18n/pcommerce-nl.po
pcommerce/shipment/pickup/i18n/pcommerce.pot
pcommerce/shipment/pickup/profiles/default/metadata.xml
pcommerce/shipment/pickup/profiles/default/propertiestool.xml