Metadata-Version: 1.0
Name: pcommerce.shipment.pickup
Version: 1.0b2
Summary: Provides a pick up shipment plugin for PCommerce
Home-page: http://raptus.com
Author: Raptus AG
Author-email: dev@raptus.com
License: GPL
Platform: UNKNOWN
Classifier: Programming Language :: Python
Classifier: Topic :: Software Development :: Libraries :: Python Modules
